setup.py
dmj_distributions/Binomialdistribution.py
dmj_distributions/Gaussiandistribution.py
dmj_distributions/Generaldistribution.py
dmj_distributions/__init__.py
dmj_distributions.egg-info/PKG-INFO
dmj_distributions.egg-info/SOURCES.txt
dmj_distributions.egg-info/dependency_links.txt
dmj_distributions.egg-info/not-zip-safe
dmj_distributions.egg-info/top_level.txt