Metadata-Version: 1.0
Name: dmj-distributions
Version: 0.1
Summary: Gaussian and Binomial distributions
Home-page: UNKNOWN
Author: David Lin
Author-email: dbspace@yahoo.com
License: UNKNOWN
Platform: UNKNOWN
